[{"StateCode":"AL","PartyCode":"GOP"},{"StateCode":"AK","PartyCode":"GOP"},{"StateCode":"AZ","PartyCode":"GOP"},{"StateCode":"AR","PartyCode":"GOP"},{"StateCode":"CA","PartyCode":"DEM"},{"StateCode":"CO","PartyCode":"DEM"},{"StateCode":"CT","PartyCode":"DEM"},{"StateCode":"DE","PartyCode":"DEM"},{"StateCode":"DC","PartyCode":"DEM"},{"StateCode":"FL","PartyCode":"GOP"},{"StateCode":"GA","PartyCode":"GOP"},{"StateCode":"HI","PartyCode":"DEM"},{"StateCode":"ID","PartyCode":"GOP"},{"StateCode":"IL","PartyCode":"DEM"},{"StateCode":"IN","PartyCode":"GOP"},{"StateCode":"IA","PartyCode":"GOP"},{"StateCode":"KS","PartyCode":"GOP"},{"StateCode":"KY","PartyCode":"GOP"},{"StateCode":"LA","PartyCode":"GOP"},{"StateCode":"MD","PartyCode":"DEM"},{"StateCode":"MA","PartyCode":"DEM"},{"StateCode":"MN","PartyCode":"DEM"},{"StateCode":"MS","PartyCode":"GOP"},{"StateCode":"MO","PartyCode":"GOP"},{"StateCode":"MT","PartyCode":"GOP"},{"StateCode":"NV","PartyCode":"DEM"},{"StateCode":"NH","PartyCode":"DEM"},{"StateCode":"NJ","PartyCode":"DEM"},{"StateCode":"NM","PartyCode":"DEM"},{"StateCode":"NY","PartyCode":"DEM"},{"StateCode":"NC","PartyCode":"GOP"},{"StateCode":"ND","PartyCode":"GOP"},{"StateCode":"OH","PartyCode":"GOP"},{"StateCode":"OK","PartyCode":"GOP"},{"StateCode":"OR","PartyCode":"DEM"},{"StateCode":"PA","PartyCode":"GOP"},{"StateCode":"RI","PartyCode":"DEM"},{"StateCode":"SC","PartyCode":"GOP"},{"StateCode":"SD","PartyCode":"GOP"},{"StateCode":"TN","PartyCode":"GOP"},{"StateCode":"TX","PartyCode":"GOP"},{"StateCode":"UT","PartyCode":"GOP"},{"StateCode":"VT","PartyCode":"DEM"},{"StateCode":"VA","PartyCode":"DEM"},{"StateCode":"WA","PartyCode":"DEM"},{"StateCode":"WV","PartyCode":"GOP"},{"StateCode":"WI","PartyCode":"GOP"},{"StateCode":"WY","PartyCode":"GOP"}]